outpostkit/__init__.py
outpostkit/base_handler.py
outpostkit/client.py
outpostkit/constants.py
outpostkit/endpoints.py
outpostkit/exceptions.py
outpostkit/files.py
outpostkit/finetuning.py
outpostkit/json.py
outpostkit/logger.py
outpostkit/predictor.py
outpostkit/resource.py
outpostkit/team.py
outpostkit/user.py
outpostkit/utils.py
outpostkit/_types/__init__.py
outpostkit/_types/endpoint.py
outpostkit/_types/entity.py
outpostkit/_types/finetuning.py
outpostkit/_types/repository.py
outpostkit/_types/team.py
outpostkit/_types/user.py
outpostkit/_utils/__init__.py
outpostkit/_utils/constants.py
outpostkit/_utils/finetuning.py
outpostkit/_utils/git.py
outpostkit/_utils/import_utils.py
outpostkit/repository/__init__.py
outpostkit/repository/lfs/__init__.py
outpostkit/repository/lfs/client.py
outpostkit/repository/lfs/exc.py
outpostkit/repository/lfs/logger.py
outpostkit/repository/lfs/transfer.py
outpostkit/repository/lfs/types.py
outpostkit-0.0.69.dist-info/LICENSE
outpostkit-0.0.69.dist-info/METADATA
outpostkit-0.0.69.dist-info/WHEEL
outpostkit-0.0.69.dist-info/top_level.txt
outpostkit-0.0.69.dist-info/RECORD
