Metadata-Version: 2.1
Name: outpostkit
Version: 0.0.69
Summary: Python client for Outpost
Author: Outpost Innovations, Inc.
License: Apache License
Project-URL: homepage, https://outpost.run
Project-URL: repository, https://github.com/outposthq/outpostkit-python
Requires-Python: >=3.8
License-File: LICENSE
Requires-Dist: httpx <1,>=0.21.0
Requires-Dist: packaging
Requires-Dist: pydantic >1
Requires-Dist: typing-extensions >=4.5.0
Provides-Extra: dev
Requires-Dist: pylint ; extra == 'dev'
Requires-Dist: pyright ; extra == 'dev'
Requires-Dist: pytest ; extra == 'dev'
Requires-Dist: pytest-asyncio ; extra == 'dev'
Requires-Dist: pytest-recording ; extra == 'dev'
Requires-Dist: respx ; extra == 'dev'
Requires-Dist: ruff ; extra == 'dev'
